{
  "kind": "home",
  "url": "https://clearvalueinvesting.com/",
  "title": "Stock & Crypto Investing Strategies | Clear Value Investing",
  "meta": {
    "description": "Unlock stock & crypto strategies to maximize returns. Learn from successful investors & make smarter decisions today!",
    "og_title": "Stock & Crypto Investing Strategies | Clear Value Investing",
    "og_description": "Unlock stock & crypto strategies to maximize returns. Learn from successful investors & make smarter decisions today!"
  },
  "headings": [
    {
      "level": "H3",
      "text": "Latest Financial And Business News"
    },
    {
      "level": "H2",
      "text": "Join Membership"
    }
  ],
  "ctas": [
    {
      "text": "Manage options",
      "tag": "A",
      "href": "https://clearvalueinvesting.com/opt-out-preferences/#cmplz-manage-consent-container"
    },
    {
      "text": "Manage services",
      "tag": "A",
      "href": "https://clearvalueinvesting.com/opt-out-preferences/#cmplz-cookies-overview"
    },
    {
      "text": "Manage {vendor_count} vendors",
      "tag": "A",
      "href": "https://clearvalueinvesting.com/opt-out-preferences/#cmplz-tcf-wrapper"
    },
    {
      "text": "Read more about these purposes",
      "tag": "A",
      "href": "https://cookiedatabase.org/tcf/purposes/"
    },
    {
      "text": "Accept",
      "tag": "BUTTON",
      "href": null
    },
    {
      "text": "Deny",
      "tag": "BUTTON",
      "href": null
    },
    {
      "text": "View preferences",
      "tag": "BUTTON",
      "href": null
    },
    {
      "text": "Save preferences",
      "tag": "BUTTON",
      "href": null
    },
    {
      "text": "View preferences",
      "tag": "A",
      "href": "https://clearvalueinvesting.com/opt-out-preferences/#cmplz-manage-consent-container"
    },
    {
      "text": "Opt-out preferences",
      "tag": "A",
      "href": "https://clearvalueinvesting.com/opt-out-preferences/"
    },
    {
      "text": "Privacy Policy",
      "tag": "A",
      "href": "https://clearvalueinvesting.com/privacy-policy/"
    },
    {
      "text": "{title}",
      "tag": "A",
      "href": "#"
    },
    {
      "text": "Skip to content",
      "tag": "A",
      "href": "#content"
    },
    {
      "text": "Education",
      "tag": "A",
      "href": "#"
    },
    {
      "text": "Stock Market",
      "tag": "A",
      "href": "https://clearvalueinvesting.com/education/stock-market/"
    },
    {
      "text": "Options Trading",
      "tag": "A",
      "href": "https://clearvalueinvesting.com/education/options-and-trading/"
    },
    {
      "text": "Index Fund",
      "tag": "A",
      "href": "https://clearvalueinvesting.com/education/index-fund/"
    },
    {
      "text": "ETFs",
      "tag": "A",
      "href": "https://clearvalueinvesting.com/education/etfs/"
    },
    {
      "text": "Crypto",
      "tag": "A",
      "href": "https://clearvalueinvesting.com/education/crypto/"
    },
    {
      "text": "Trading & Chart Analysis",
      "tag": "A",
      "href": "https://clearvalueinvesting.com/education/trading-chart-analysis/"
    },
    {
      "text": "Taxes",
      "tag": "A",
      "href": "https://clearvalueinvesting.com/education/taxes/"
    },
    {
      "text": "Budgeting",
      "tag": "A",
      "href": "https://clearvalueinvesting.com/education/budgeting/"
    },
    {
      "text": "Retirement",
      "tag": "A",
      "href": "https://clearvalueinvesting.com/education/retirement/"
    },
    {
      "text": "Real Estate",
      "tag": "A",
      "href": "https://clearvalueinvesting.com/education/real-estate/"
    },
    {
      "text": "Tools",
      "tag": "A",
      "href": "#"
    },
    {
      "text": "Templates",
      "tag": "A",
      "href": "https://clearvalueinvesting.com/tools/templates/"
    },
    {
      "text": "Home Affordability Calculator",
      "tag": "A",
      "href": "https://clearvalueinvesting.com/tools/calculators/home-affordability/"
    },
    {
      "text": "Productivity Checklist​",
      "tag": "A",
      "href": "https://clearvalueinvesting.com/tools/calculators/productivity-checklist/"
    },
    {
      "text": "Community",
      "tag": "A",
      "href": "#"
    },
    {
      "text": "Blog",
      "tag": "A",
      "href": "https://clearvalueinvesting.com/blog/"
    }
  ],
  "body_text": "Skip to content\nOur mission is to help you obtain financial freedom. Checkout Our Youtube Channel\nEducation\nTools\nCommunity\nLogin\nMembership\nContact\nEducation\nTools\nCommunity\nLogin\nMembership\nContact\nS&P 500\n$6,827.26\n+98.46\n1.46%\nDow Jones\n$47,337.60\n+350.50\n0.75%\nNASDAQ\n$23,516.52\n+511.98\n2.23%\nGold\n--\nSilver\n--\nOil\n$109.76\nBitcoin\n--\nEthereum\n--\nSolana\n--\nCPI (Inflation Tracker)\n3.80%\n30-Year Mortgage Rate\n--\nAverage Gas Prices\n$4.50\n2-Year U.S. Treasury Yield\n3.80%\n10-Year Treasury Yield\n4.32%\n30-Year Treasury Yield\n4.91%\nLatest Financial And Business News\nAccor and Shoreline sign agreement for Nigerian hotel development\n‘I nearly made a major misstep’: I claimed my Social Security benefits at 64 instead of 70. Here’s why.\n“It’s remarkable — and discouraging — how many people are disengaged from their own financial lives.”\nBoeing could finally reignite its China business. Will that breathe new life into its stock?\nWall Street is hoping Boeing is about to announce a big order from China, cementing its turnaround.\nTax reforms set to accelerate Australia’s shift from stock-picking to ETF investing\nNextpower Stock Hits 52-Week High - Here's Why\nBoring Beats Brilliant: How a Utilities ETF Has Quietly Trounced the S & P 500 in Nearly Every Recession This Century\nOil prices dip ahead of Trump-Xi talks amid Iran tensions\nCopper prices are now at their highest level on record. AI is only part of the story.\nCopper refining now has a Strait of Hormuz problem.\nDow Jones Futures: Nvidia's Huang Joins Trump's China Trip; Sandisk, Micron, Intel Rebound\n1 Clean Energy Stock to Buy While Oil Prices Are High\nEd Yardeni just set the highest S&P 500 target on Wall Street — but warns a meltdown may soon follow\nRTX Corporation (RTX) Receives Order For SharpSight radars from Blue Raven\nJoin Membership\nGet full access to the exclusive content that our team has compiled through extensive research and elevate your knowledge to new heights. Unlock insights, analyses, and strategies that can be used as a framework to help you in your investment journey.\nSign Up\nTerms of Use | Privacy Policy\n© ClearValue Investing 2026 — All rights reserved.​\nTwitter\nYoutube"
}